[{"name":"Radio Pulsar","logo":"","category":"","url":"http:\/\/pulsarouagadougou.ice.infomaniak.ch\/pulsarouagadougou-64.mp3"},{"name":"Africa N°1","logo":"","category":"","url":"http:\/\/icepe14.infomaniak.ch:80\/african1paris-128"},{"name":"Radio Omega FM Ouaga","logo":"","category":"","url":"http:\/\/37.187.112.148:8000\/stream"},{"name":"Africa N 1 | Ouagadougou | African Music|Public Radio|French","logo":"","url":"http:\/\/african1paris.ice.infomaniak.ch\/african1paris-64.mp3"},{"name":"Ouaga FM | Ouagadougou | African Music|French","logo":"","url":"http:\/\/fluoz-12.radiojar.com\/qzv5str7mceuv"},{"name":"Radio Maria | Kupela | Religious","logo":"","url":"http:\/\/dreamsiteradiocp2.com:8050\/;stream.nsv"},{"name":"Studio Geithain Radio","logo":"","category":"Ouagadougou","url":"http:\/\/listen.radionomy.com\/studio-geithain"},{"name":"Africa N°1","logo":"","category":"","url":"http:\/\/icepe11.infomaniak.ch\/african1paris-128"}]