[{"name":"FM 100.5 News Network","logo":"http:\/\/static.mytuner.mobi\/media\/radios\/kZfaeWupWQ.jpeg","category":"News","url":"http:\/\/rstream.mcot.net:8000\/fm1005"},{"name":"90 ลูกทุ่ง รักไทย","logo":"http:\/\/static.mytuner.mobi\/media\/radios\/vxc3vq6dxy8j.jpeg","url":"http:\/\/radio11.plathong.net:8896\/;stream.mp3"},{"name":"สถานีวิทุยส่วนภูมิภาค MCOT Radio ยะลา","logo":"http:\/\/static.mytuner.mobi\/media\/radios\/nmbsphpxar78.png","url":"http:\/\/rstream.mcot.net:9102\/;.mp3"},{"name":"Alpharadio","logo":"http:\/\/static.mytuner.mobi\/media\/radios\/pvnexm9gvjva.jpg","url":"http:\/\/radio12.plathong.net:7338\/"},{"name":"Sangkaew Radio 90.2 FM","logo":"http:\/\/static.mytuner.mobi\/media\/radios\/tewnb6eyksyp.png","url":"http:\/\/radio.nkradio.info:8002\/;stream.mp3"},{"name":"สถานีวิทุยส่วนภูมิภาค MCOT Radio ระนอง","logo":"http:\/\/static.mytuner.mobi\/media\/radios\/x3ta5xr9m6rv.png","url":"http:\/\/rstream.mcot.net:9016\/;.mp3"},{"name":"Myfamily Radio","logo":"http:\/\/static.mytuner.mobi\/media\/radios\/jjvx69kr8aje.jpg","url":"http:\/\/ohmi-design.com:9156\/;"},{"name":"BBC World Service","logo":"http:\/\/static.mytuner.mobi\/media\/radios\/EcrBmf5qEr.jpg","category":"News","url":"http:\/\/bbcwssc.ic.llnwd.net\/stream\/bbcwssc_mp1_ws-eieuk"},{"name":"My Ready Web","logo":"http:\/\/static.mytuner.mobi\/media\/radios\/thdyrly5n8nv.jpg","url":"http:\/\/radio11.plathong.net:8050\/"},{"name":"สถานีวิทุยส่วนภูมิภาค MCOT Radio นราธิวาส","logo":"http:\/\/static.mytuner.mobi\/media\/radios\/dw3l9h5w7r3z.png","url":"http:\/\/rstream.mcot.net:9096\/;.mp3"},{"name":"Radio Chiangmai 93.2 FM","logo":"http:\/\/static.mytuner.mobi\/media\/radios\/chNn37u4A7.png","url":"http:\/\/prdonline.prd.go.th:8118\/"},{"name":"Parwaaz Radio","logo":"http:\/\/static.mytuner.mobi\/media\/radios\/abwmkkpz7cye.jpg","url":"http:\/\/192.99.8.192:3404\/"},{"name":"สถานีวิทุยส่วนภูมิภาค MCOT Radio หนองคาย","logo":"http:\/\/static.mytuner.mobi\/media\/radios\/z4jzxahn4rqe.png","url":"http:\/\/rstream.mcot.net:9042\/;.mp3"},{"name":"Big FM","logo":"http:\/\/static.mytuner.mobi\/media\/radios\/246pd75kpjkt.png","url":"http:\/\/media.login.in.th:8195\/;stream.mp3"},{"name":"พบกันด้วยธรรมะ","logo":"http:\/\/static.mytuner.mobi\/media\/radios\/yJ6b8bJwjE.png","url":"http:\/\/radio.portradiothai.com:6002\/;stream.mp3"},{"name":"Ondio.in New","logo":"http:\/\/static.mytuner.mobi\/media\/radios\/fupLAccBRh.png","category":"Top 40","url":"http:\/\/112.121.150.133:8020\/stream?1543922698828"},{"name":"Wink.in.TH","logo":"http:\/\/static.mytuner.mobi\/media\/radios\/94lm9wuee6pp.png","category":"Pop Music","url":"http:\/\/radio.wink.in.th\/;"},{"name":"Sweetezyradio","logo":"http:\/\/static.mytuner.mobi\/media\/radios\/tb7zsazv6mgj.png","url":"http:\/\/103.22.182.153:8524\/"},{"name":"เพลงสตริงเก่า Eingdoi Radio","logo":"http:\/\/static.mytuner.mobi\/media\/radios\/6pvkygbpw8v5.jpg","url":"http:\/\/ohmi-design.com:8170\/;"},{"name":"GET 102.5 FM","logo":"http:\/\/static.mytuner.mobi\/media\/radios\/unyt8dpmtt7k.png","category":"Variety","url":"http:\/\/get1025.plathong.net:7004\/;stream.mp3"},{"name":"สถานีวิทุยส่วนภูมิภาค MCOT Radio สุรินทร์","logo":"http:\/\/static.mytuner.mobi\/media\/radios\/qr743esn7czh.png","url":"http:\/\/rstream.mcot.net:9056\/;.mp3"},{"name":"ปวงข้าพระพุทธเจ้า","logo":"http:\/\/static.mytuner.mobi\/media\/radios\/zwwtx32zbhbx.jpg","url":"http:\/\/radio12.plathong.net:7002\/"},{"name":"Fung Fung Fung","logo":"http:\/\/static.mytuner.mobi\/media\/radios\/Yb3G5xc8HF.jpeg","category":"Easy Listening","url":"http:\/\/119.59.125.182:8064\/;"},{"name":"MadChima","logo":"http:\/\/static.mytuner.mobi\/media\/radios\/drzkrgcysrsk.jpg","url":"http:\/\/radio.hostinglotus.com:6008\/"},{"name":"Radio Thailand Lampang","logo":"null","category":"News","url":"http:\/\/202.129.35.2:8022\/"},{"name":"สถานีวิทุยส่วนภูมิภาค MCOT Radio ประจวบคีรีขันธ์","logo":"http:\/\/static.mytuner.mobi\/media\/radios\/ukyfrtg5egdk.png","url":"http:\/\/rstream.mcot.net:9012\/;.mp3"},{"name":"Ondio.in Old","logo":"http:\/\/static.mytuner.mobi\/media\/radios\/zMhgkXweTG.png","category":"Oldies","url":"http:\/\/112.121.150.133:8022\/stream?1543922402145"},{"name":"สถานีวิทุยส่วนภูมิภาค MCOT Radio ลำพูน","logo":"http:\/\/static.mytuner.mobi\/media\/radios\/kdrz8hh6pb4d.png","url":"http:\/\/rstream.mcot.net:9068\/;.mp3"},{"name":"HITZ 955","logo":"http:\/\/static.mytuner.mobi\/media\/radios\/XE76PXWUQ4.png","category":"Pop Music","url":"https:\/\/wzedge1.becteroradio.com\/Hitz\/Hitz-Listen-Med\/playlist.m3u8"},{"name":"สถานีวิทุยส่วนภูมิภาค MCOT Radio กาญจนบุรี","logo":"http:\/\/static.mytuner.mobi\/media\/radios\/e9q3zrql58fg.png","url":"http:\/\/rstream.mcot.net:9010\/;.mp3"},{"name":"NBT - Radio Thailand 95.5 FM","logo":"http:\/\/static.mytuner.mobi\/media\/radios\/rtygs9RD27.png","category":"News","url":"http:\/\/prdonline.prd.go.th:8206"},{"name":"สถานีวิทุยส่วนภูมิภาค MCOT Radio ชัยภูมิ","logo":"http:\/\/static.mytuner.mobi\/media\/radios\/fmeexew2wpyz.png","url":"http:\/\/rstream.mcot.net:9046\/;.mp3"},{"name":"สถานีวิทุยส่วนภูมิภาค MCOT Radio กำแพงเพชร","logo":"http:\/\/static.mytuner.mobi\/media\/radios\/r96yqadwmsrk.png","url":"http:\/\/rstream.mcot.net:9002\/;.mp3"},{"name":"สถานีวิทุยส่วนภูมิภาค MCOT Radio ลำปาง","logo":"http:\/\/static.mytuner.mobi\/media\/radios\/78dwuzgjfqmh.png","url":"http:\/\/rstream.mcot.net:9074\/;.mp3"},{"name":"สถานีวิทุยส่วนภูมิภาค MCOT Radio สุโขทัย","logo":"http:\/\/static.mytuner.mobi\/media\/radios\/bqfnyftmuyta.png","url":"http:\/\/rstream.mcot.net:9080"},{"name":"Radio Music Hitz","logo":"http:\/\/static.mytuner.mobi\/media\/radios\/e4frz9uwfq3r.jpg","url":"http:\/\/112.121.150.133:8122\/live"},{"name":"สถานีวิทุยส่วนภูมิภาค MCOT Radio สตูล","logo":"http:\/\/static.mytuner.mobi\/media\/radios\/kk7m4kjrzlrh.png","url":"http:\/\/rstream.mcot.net:9106\/;.mp3"},{"name":"สถานีวิทุยส่วนภูมิภาค MCOT Radio นครพนม","logo":"http:\/\/static.mytuner.mobi\/media\/radios\/u8nlkyjblb4y.png","url":"http:\/\/rstream.mcot.net:9032\/;.mp3"},{"name":"98 อีสาน เอฟเอ็ม","logo":"http:\/\/static.mytuner.mobi\/media\/radios\/naazdc5h6kuz.png","url":"http:\/\/radio11.spicymkt.com:8900\/;stream.mp3"},{"name":"Modern Radio Pichit","logo":"http:\/\/static.mytuner.mobi\/media\/radios\/gqjatzhhxyju.jpg","url":"http:\/\/rstream.mcot.net:9004\/;.mp3"},{"name":"Blessing FM","logo":"http:\/\/static.mytuner.mobi\/media\/radios\/nhf5ax2jgfxz.png","category":"Tamil","url":"http:\/\/eu2.fastcast4u.com:3634\/"},{"name":"Modern Radio Yasothon","logo":"http:\/\/static.mytuner.mobi\/media\/radios\/zgevnbzccjna.jpg","url":"http:\/\/rstream.mcot.net:9052\/;.mp3"},{"name":"คลื่นความรู้คู่คุณธรรม Like Station AM 1494","logo":"http:\/\/static.mytuner.mobi\/media\/radios\/3qHjfM9pJn.png","url":"http:\/\/rstream.mcot.net:8000\/am1494"},{"name":"FM 99 Active Radio คลื่นเมืองไทยแข็งแรง","logo":"http:\/\/static.mytuner.mobi\/media\/radios\/WHNexhbsca.png","category":"Sports","url":"https:\/\/mcotdigital-gvwieh.cdn.byteark.com\/radiocdn_edge\/fm99.stream_aac\/playlist.m3u8"},{"name":"Friend 105.7 Chiangmai","logo":"http:\/\/static.mytuner.mobi\/media\/radios\/enfwkbl3q8l2.jpg","url":"http:\/\/112.121.150.133:9338\/"},{"name":"NBT - Radio Thailand 92.5 FM","logo":"http:\/\/static.mytuner.mobi\/media\/radios\/HCBkacVe2p.png","category":"News","url":"http:\/\/prdonline.prd.go.th:8202"},{"name":"97 Mazz Radio","logo":"http:\/\/static.mytuner.mobi\/media\/radios\/g88q6quvcp3n.jpg","url":"http:\/\/radio1.comgig.com:4096\/;stream.m4a"},{"name":"สตริงใหม่ Pophits Radio Eingdoi","logo":"http:\/\/static.mytuner.mobi\/media\/radios\/mbtcqejrg3ca.jpg","category":"Top 40","url":"http:\/\/ohmi-design.com:9090\/"},{"name":"Family Radio FM 93.7","logo":"http:\/\/static.mytuner.mobi\/media\/radios\/6dZnDVpjUj.png","url":"https:\/\/radio14.plathong.net\/7298\/;stream.mp3"},{"name":"SMM Sport Radio 96","logo":"http:\/\/static.mytuner.mobi\/media\/radios\/XGLtJAdrxs.png","category":"Sports","url":"http:\/\/110.164.48.215:8000\/smmradio"},{"name":"93.5 Happy Time","logo":"http:\/\/static.mytuner.mobi\/media\/radios\/nns72bppeakv.png","url":"http:\/\/radio99.servradio.com:9336\/;stream.mp3"},{"name":"สถานีวิทุยส่วนภูมิภาค MCOT Radio ขอนแก่น","logo":"http:\/\/static.mytuner.mobi\/media\/radios\/n7cnmr5flp47.png","url":"http:\/\/rstream.mcot.net:9030\/;.mp3"},{"name":"FM91 Pattaya Mundee","logo":"http:\/\/static.mytuner.mobi\/media\/radios\/k8msvtjpbcpn.png","category":"Hot AC","url":"http:\/\/onair22.onair.network:8068\/stream.mp3"},{"name":"88.5 EDS FM","logo":"http:\/\/static.mytuner.mobi\/media\/radios\/tlh9ufnzq7bn.png","url":"http:\/\/media.login.in.th:1290\/;stream.mp3"},{"name":"Capitol FM","logo":"http:\/\/static.mytuner.mobi\/media\/radios\/NvUAj9bf8W.png","url":"http:\/\/atlanticthai.primcast.com:5898\/"},{"name":"SBT Radio (หลวงตาบัว Luangta Maha Bua)","logo":"http:\/\/static.mytuner.mobi\/media\/radios\/6lzvhjyy4fs7.jpeg","category":"Religious","url":"http:\/\/202.142.203.28:8000\/siangdham.mp3"},{"name":"NBT - Radio Education Center","logo":"http:\/\/static.mytuner.mobi\/media\/radios\/RgZwkGWveY.png","category":"Educational","url":"http:\/\/prdonline.prd.go.th:8018"},{"name":"96.5 คลื่นความคิด (Thinking Radio)","logo":"http:\/\/static.mytuner.mobi\/media\/radios\/TnCWW43MyK.png","url":"https:\/\/mcotdigital-9ksau4.cdn.byteark.com\/radiocdn_edge\/fm965.stream_aac\/playlist.m3u8"},{"name":"สถานีวิทุยส่วนภูมิภาค MCOT Radio พะเยา","logo":"http:\/\/static.mytuner.mobi\/media\/radios\/nrtuag72sfau.png","url":"http:\/\/rstream.mcot.net:9062\/;.mp3"},{"name":"สถานีวิทุยส่วนภูมิภาค MCOT Radio ระยอง","logo":"http:\/\/static.mytuner.mobi\/media\/radios\/vs6vd52jqp6v.png","url":"http:\/\/rstream.mcot.net:9026\/;.mp3"},{"name":"Trang Chinh","logo":"http:\/\/static.mytuner.mobi\/media\/radios\/vnempwj27eag.png","url":"http:\/\/162.244.80.118:3092\/;stream.mp3"},{"name":"Sangamum Radio","logo":"http:\/\/static.mytuner.mobi\/media\/radios\/zhgctjjncs4w.png","url":"http:\/\/eu2.fastcast4u.com:3628\/"},{"name":"สถานีเพลงสากล (Request Radio: International Music)","logo":"http:\/\/static.mytuner.mobi\/media\/radios\/pFkhvW6wPL.png","category":"Variety","url":"http:\/\/27.254.142.208:8400\/;?_=0.7654001104191831"},{"name":"Modern 98.7 FM","logo":"http:\/\/static.mytuner.mobi\/media\/radios\/s6ymtarkmare.jpg","url":"http:\/\/112.121.150.133:9102\/;stream.nsv"},{"name":"RequestRadio เพลงสากล","logo":"http:\/\/static.mytuner.mobi\/media\/radios\/Shf4dp98ac.png","url":"http:\/\/27.254.142.208:8100\/;?_=0.647235297273889"},{"name":"Muingtest Radio","logo":"http:\/\/static.mytuner.mobi\/media\/radios\/shmc6hvsrzn7.jpg","category":"90s","url":"http:\/\/ohmi-design.com:8364\/"},{"name":"Singh Naad","logo":"http:\/\/static.mytuner.mobi\/media\/radios\/cefgffnldezj.png","url":"http:\/\/s8.voscast.com:9366\/"},{"name":"สถานีวิทุยส่วนภูมิภาค MCOT Radio หลังสวน","logo":"http:\/\/static.mytuner.mobi\/media\/radios\/zmkkynzdzcrt.png","url":"http:\/\/rstream.mcot.net:9018\/;.mp3"},{"name":"FM9525","logo":"http:\/\/static.mytuner.mobi\/media\/radios\/7gcse9xgfuvz.png","url":"http:\/\/radio.dwebsalehost.com:9082"},{"name":"สถานีวิทุยส่วนภูมิภาค MCOT Radio สกลนคร","logo":"http:\/\/static.mytuner.mobi\/media\/radios\/mw8bqxjhqhsn.png","url":"http:\/\/rstream.mcot.net:9040\/;.mp3"},{"name":"NBT - Radio Thailand 97.0 FM","logo":"http:\/\/static.mytuner.mobi\/media\/radios\/CPDCFXTyaw.png","category":"News","url":"http:\/\/prdonline.prd.go.th:8208"},{"name":"FM 101.0 Tourist Radio Krabi","logo":"http:\/\/static.mytuner.mobi\/media\/radios\/gmbxy3smyusn.jpg","url":"http:\/\/radio12.plathong.net:8672\/"},{"name":"Vallamayinthoni","logo":"http:\/\/static.mytuner.mobi\/media\/radios\/8zh7rc5xgnvy.png","url":"http:\/\/s7.voscast.com:8302\/"},{"name":"YES Radio thai Family (TH Only)","logo":"http:\/\/static.mytuner.mobi\/media\/radios\/dqhdnczntxrn.png","url":"http:\/\/27.254.65.244:8000\/;"},{"name":"101 Rrone FM Radio","logo":"http:\/\/static.mytuner.mobi\/media\/radios\/LwKKkQyUcD.png","category":"Variety","url":"http:\/\/media.login.in.th:8135\/;stream.mp3"},{"name":"The Shock FM101","logo":"http:\/\/static.mytuner.mobi\/media\/radios\/32nfvg7pxmdt.png","url":"http:\/\/103.58.149.186:8135\/stream\/1\/"},{"name":"Surat City Radio 102.75","logo":"http:\/\/static.mytuner.mobi\/media\/radios\/zeyvsg9vqvkk.png","url":"http:\/\/202.57.162.183:8000\/fm10275"},{"name":"NR Sports Radio","logo":"http:\/\/static.mytuner.mobi\/media\/radios\/g6g9aj2cgd9t.png","category":"Sports","url":"http:\/\/112.121.151.133:8000\/live"},{"name":"Fabulous 103.0 FM","logo":"http:\/\/static.mytuner.mobi\/media\/radios\/zutxddwzvume.png","url":"http:\/\/thai-host.com:8100\/pattaya103.ogg"},{"name":"Yesterday 106.5 FM","logo":"http:\/\/static.mytuner.mobi\/media\/radios\/fzc5x62n4qk8.jpg","url":"http:\/\/radio4.thzhost.com:4122\/"},{"name":"สถานีวิทุยส่วนภูมิภาค MCOT Radio ภูเก็ต","logo":"http:\/\/static.mytuner.mobi\/media\/radios\/hveka8qsjrjs.png","url":"http:\/\/rstream.mcot.net:9088\/;.mp3"},{"name":"iCecy Radio 93.7 FM","logo":"http:\/\/static.mytuner.mobi\/media\/radios\/guppddqmkmuc.jpg","url":"http:\/\/radio11.plathong.net:8254\/"},{"name":"สถานีวิทยุราชดำริสัมพันธ์ 1 FM","logo":"http:\/\/static.mytuner.mobi\/media\/radios\/C3eXyf6kyj.jpeg","url":"http:\/\/radio.servradio.com:8614\/"},{"name":"สถานีวิทุยส่วนภูมิภาค MCOT Radio ตรัง","logo":"http:\/\/static.mytuner.mobi\/media\/radios\/degnqcjrn9vs.png","url":"http:\/\/rstream.mcot.net:9092\/;.mp3"},{"name":"CH19 FM","logo":"http:\/\/static.mytuner.mobi\/media\/radios\/3JDhTmZUBQ.jpg","category":"International","url":"http:\/\/174.37.159.206:8050\/"},{"name":"สถานีวิทุยส่วนภูมิภาค MCOT Radio ตราด","logo":"http:\/\/static.mytuner.mobi\/media\/radios\/5pze8anpytts.png","url":"http:\/\/rstream.mcot.net:9024\/;.mp3"},{"name":"89.5 SWEET FM","logo":"http:\/\/static.mytuner.mobi\/media\/radios\/yQaa92p5zN.jpeg","url":"http:\/\/radio.spicymkt.com:9230\/;stream"},{"name":"Phuket LIVE 89.5 FM","logo":"http:\/\/static.mytuner.mobi\/media\/radios\/w7KSxyGFgt.png","url":"http:\/\/radio4.thzhost.com:4118\/;stream\/1"},{"name":"FM89.5 OnAir Hatyai - NBT Songkhla","logo":"http:\/\/static.mytuner.mobi\/media\/radios\/uv387vyyrurw.jpg","category":"Adult Contemporary","url":"http:\/\/link.onair.network:8056\/stream.mp3"},{"name":"สถานีวิทุยส่วนภูมิภาค MCOT Radio พัทลุง","logo":"http:\/\/static.mytuner.mobi\/media\/radios\/hxdte4upxurn.png","url":"http:\/\/rstream.mcot.net:9100\/;.mp3"},{"name":"Musichitz Radio Looktug","logo":"http:\/\/static.mytuner.mobi\/media\/radios\/f2vyamxef6zz.png","url":"http:\/\/112.121.150.133:9386\/stream"},{"name":"Top View Point Radio","logo":"http:\/\/static.mytuner.mobi\/media\/radios\/ewd3cgawxfsf.png","url":"http:\/\/radio12.plathong.net:8274\/"},{"name":"สถานีวิทุยส่วนภูมิภาค MCOT Radio แม่ฮ่องสอน","logo":"http:\/\/static.mytuner.mobi\/media\/radios\/46dfspn3zfuf.png","url":"http:\/\/rstream.mcot.net:9064\/;.mp3"},{"name":"Derby International","logo":"http:\/\/static.mytuner.mobi\/media\/radios\/7n8raqcrz5ph.png","url":"http:\/\/37.59.42.207:8226\/"},{"name":"สถานีวิทุยส่วนภูมิภาค MCOT Radio อุบลราชธานี","logo":"http:\/\/static.mytuner.mobi\/media\/radios\/eqasz9yyagbg.png","url":"http:\/\/rstream.mcot.net:9058\/;.mp3"},{"name":"Modern Radio Srisaket","logo":"http:\/\/static.mytuner.mobi\/media\/radios\/37ka2xuwcabq.jpg","url":"http:\/\/rstream.mcot.net:9054\/;.mp3"},{"name":"BTR blues","logo":"http:\/\/static.mytuner.mobi\/media\/radios\/83prnnk7dv9y.png","category":"Blues","url":"http:\/\/69.46.24.226:7056\/stream"},{"name":"Chiang Mai Radio 93.7 FM","logo":"http:\/\/static.mytuner.mobi\/media\/radios\/p6wcevjnx8ka.png","url":"http:\/\/112.121.151.133:8124\/live"},{"name":"94 Chat FM","logo":"http:\/\/static.mytuner.mobi\/media\/radios\/63b4dv5tagnu.jpg","url":"http:\/\/c1.hostpleng.cloud:8009\/live2"},{"name":"สถานีวิทุยส่วนภูมิภาค MCOT Radio กาฬสินธุ์","logo":"http:\/\/static.mytuner.mobi\/media\/radios\/xsuhdyqz2cxw.png","url":"http:\/\/rstream.mcot.net:9028\/;.mp3"},{"name":"EFM 104.5","logo":"http:\/\/static.mytuner.mobi\/media\/radios\/Ck8sVEmWdv.jpg","category":"Top 40","url":"https:\/\/real4.atimemedia.com\/efm"},{"name":"สถานีวิทุยส่วนภูมิภาค MCOT Radio ร้อยเอ็ด","logo":"http:\/\/static.mytuner.mobi\/media\/radios\/awvcd59bbndf.png","url":"http:\/\/rstream.mcot.net:9036\/;.mp3"},{"name":"PNU Radio FM 92.25 Narathiwat","logo":"http:\/\/static.mytuner.mobi\/media\/radios\/kugarxsvdnqz.png","url":"http:\/\/radio11.plathong.net:8548\/"},{"name":"NBT - Radio Thailand 819 AM","logo":"http:\/\/static.mytuner.mobi\/media\/radios\/xCvkf5Ub6P.png","category":"News","url":"http:\/\/prdonline.prd.go.th:8212"},{"name":"Kiss 91.7 FM","logo":"http:\/\/static.mytuner.mobi\/media\/radios\/YSfN8g5qrR.png","category":"Classic Rock","url":"http:\/\/s1.thailandstreaming.net:8020\/kiss.mp3"},{"name":"Star Radio 95.2 FM","logo":"http:\/\/static.mytuner.mobi\/media\/radios\/ec942tpr9qdf.png","url":"http:\/\/112.121.151.133:8152\/live"},{"name":"Mellow 97.5 FM","logo":"http:\/\/static.mytuner.mobi\/media\/radios\/geZgfjMRxE.jpg","url":"https:\/\/mcotdigital-3bgyw0.cdn.byteark.com\/radiocdn_edge\/fm975.stream_aac\/playlist.m3u8"},{"name":"Pattaya Guide Radio","logo":"http:\/\/static.mytuner.mobi\/media\/radios\/hrgkuffmupdf.png","url":"http:\/\/67.225.148.237:9306\/"},{"name":"VOA Thai","logo":"http:\/\/static.mytuner.mobi\/media\/radios\/CfbKMK6tdw.png","url":"http:\/\/voa-51.ng.akacast.akamaistream.net\/7\/663\/322063\/v1\/ibb.akacast.akamaistream.net\/voa-51"},{"name":"Chill FM","logo":"http:\/\/static.mytuner.mobi\/media\/radios\/FRgnKAsHgV.jpg","category":"Chillout","url":"https:\/\/real4.atimemedia.com\/chill?id=1551096080678"},{"name":"WatBuddhawas","logo":"http:\/\/static.mytuner.mobi\/media\/radios\/p979fseu2pct.jpg","url":"http:\/\/radio2.serverradio.net:8060\/;"},{"name":"สถานีวิทุยส่วนภูมิภาค MCOT Radio พังงา","logo":"http:\/\/static.mytuner.mobi\/media\/radios\/qkulqddc9nl9.png","url":"http:\/\/rstream.mcot.net:9086\/;.mp3"},{"name":"Fat 93 Radio เชียงราย","logo":"http:\/\/static.mytuner.mobi\/media\/radios\/25drz35wb3pm.png","url":"http:\/\/112.121.151.133:8272\/stream"},{"name":"City Radio Pattaya","logo":"http:\/\/static.mytuner.mobi\/media\/radios\/vBjbAq89jv.jpg","category":"Top 40","url":"http:\/\/103.22.182.14:8074\/1\/"},{"name":"สถานีวิทุยส่วนภูมิภาค MCOT Radio เชียงใหม่","logo":"http:\/\/static.mytuner.mobi\/media\/radios\/nb2ery3pqq9y.png","url":"http:\/\/rstream.mcot.net:9066\/;.mp3"},{"name":"ìNakara Radio Online","logo":"http:\/\/static.mytuner.mobi\/media\/radios\/s7zcrnspvaa6.jpg","url":"http:\/\/112.121.150.133:8038\/"},{"name":"NBT - Radio Thailand 891 AM","logo":"http:\/\/static.mytuner.mobi\/media\/radios\/eEgYfHVbqa.png","category":"News","url":"http:\/\/prdonline.prd.go.th:8216"},{"name":"Best Radio","logo":"http:\/\/static.mytuner.mobi\/media\/radios\/Xe9u3QLgrX.png","category":"Pop Music","url":"http:\/\/listen.radionomy.com\/best---radio"},{"name":"Phuket FM Radio (Phuket Island Radio)","logo":"http:\/\/static.mytuner.mobi\/media\/radios\/2xhN8q6Bhc.png","category":"Dance","url":"http:\/\/stream.phuketfmradio.com\/pfmMP3"},{"name":"Surat City Radio 91.00","logo":"http:\/\/static.mytuner.mobi\/media\/radios\/2vlgrphmmzdp.png","url":"http:\/\/202.57.162.183:8000\/fm91surat"},{"name":"Cat Radio","logo":"http:\/\/static.mytuner.mobi\/media\/radios\/7DqAhMKgcr.jpeg","url":"http:\/\/203.145.115.35\/CatRadio\/CatRadio-High\/playlist.m3u8"},{"name":"Mcot Radio 102.0 FM Surat Thani","logo":"http:\/\/static.mytuner.mobi\/media\/radios\/wbu3vFWvq4.png","url":"http:\/\/rstream.mcot.net:9090\/;"},{"name":"สถานีวิทุยส่วนภูมิภาค MCOT Radio ปัตตานี","logo":"http:\/\/static.mytuner.mobi\/media\/radios\/zds2n2m76wyg.png","url":"http:\/\/rstream.mcot.net:9098\/;.mp3"},{"name":"Thai Radio","logo":"http:\/\/static.mytuner.mobi\/media\/radios\/kkttbzv9j879.png","category":"Pop Music","url":"http:\/\/5.133.182.164:25581\/;&type=mp3"},{"name":"สถานีวิทุยส่วนภูมิภาค MCOT Radio ชุมพร","logo":"http:\/\/static.mytuner.mobi\/media\/radios\/tkdqax3wvfev.png","url":"http:\/\/rstream.mcot.net:9014\/;.mp3"},{"name":"V-Giff","logo":"http:\/\/static.mytuner.mobi\/media\/radios\/hrkbeuqbpvep.jpg","url":"http:\/\/radio4.thzhost.com:4014\/"},{"name":"Shan Online Radio","logo":"http:\/\/static.mytuner.mobi\/media\/radios\/xth4hapbugfp.png","url":"http:\/\/radio11.plathong.net:7114\/"},{"name":"NBT - Radio Thailand 88 FM","logo":"http:\/\/static.mytuner.mobi\/media\/radios\/WSsQSY9jEs.png","category":"News","url":"http:\/\/prdonline.prd.go.th:8200"},{"name":"Radio Rongdhonu","logo":"http:\/\/static.mytuner.mobi\/media\/radios\/wjpxbmb4xalh.jpg","url":"http:\/\/212.83.150.15:8448\/"},{"name":"มิติข่าว 90.5 Smart Bomb","logo":"http:\/\/static.mytuner.mobi\/media\/radios\/cdsw45cqvjte.jpg","url":"http:\/\/live3.smartbomb.co.th:8624\/;stream.mp3"},{"name":"สถานีวิทุยส่วนภูมิภาค MCOT Radio เชียงราย","logo":"http:\/\/static.mytuner.mobi\/media\/radios\/e6qvtshx8e64.png","url":"http:\/\/rstream.mcot.net:9060\/;.mp3"},{"name":"MUN FM","logo":"http:\/\/static.mytuner.mobi\/media\/radios\/N96spp6XLf.png","url":"http:\/\/radio2.thzhost.com:4018"},{"name":"106 ครอบครัวข่าว","logo":"http:\/\/static.mytuner.mobi\/media\/radios\/5vfxsvfwzgqm.png","url":"http:\/\/radio12.plathong.net:8648\/;stream.mp3"},{"name":"ลูกทุ่งมหานคร อสมท FM 95","logo":"http:\/\/static.mytuner.mobi\/media\/radios\/zbX4rrqNu8.png","url":"http:\/\/mcotdigital-1wevsb.cdn.byteark.com\/radiocdn_edge\/fm95.stream_aac\/playlist.m3u8"},{"name":"MCOT Modern Radio","logo":"http:\/\/static.mytuner.mobi\/media\/radios\/7CdaEWFPHD.png","category":"Local","url":"http:\/\/rstream.mcot.net:9066\/"},{"name":"NBT - Radio Thailand 105 FM","logo":"http:\/\/static.mytuner.mobi\/media\/radios\/evaz3k7Nkm.png","category":"News","url":"http:\/\/prdonline.prd.go.th:8210"},{"name":"Sunshine Radio","logo":"http:\/\/static.mytuner.mobi\/media\/radios\/6jeXt8rZf5.png","url":"http:\/\/icecast.piesoft.net:8000\/pat"},{"name":"FM98 Dongtan Beach Pattaya","logo":"http:\/\/static.mytuner.mobi\/media\/radios\/fsrwmysdpfxp.jpg","category":"Adult Contemporary","url":"http:\/\/202.129.207.86:8056\/stream"},{"name":"เพลงลูกทุ่ง Request Radio Country Music","logo":"http:\/\/static.mytuner.mobi\/media\/radios\/GSJSFuqNnJ.png","url":"http:\/\/27.254.142.208:8200"},{"name":"t.a.b. radio 2","logo":"http:\/\/static.mytuner.mobi\/media\/radios\/gn5vyagee4hy.png","url":"http:\/\/103.22.182.145:8400\/tabradio2\/;"},{"name":"Wat","logo":"http:\/\/static.mytuner.mobi\/media\/radios\/dlaqq6tswujg.png","category":"Talk","url":"http:\/\/radio1.siamlivehost.com:8001"},{"name":"Pongpan Radio","logo":"http:\/\/static.mytuner.mobi\/media\/radios\/8qVGCNNArp.png","category":"Pop Music","url":"http:\/\/radio.portradiothai.com:6010"},{"name":"PPP 97.2 FM","logo":"http:\/\/static.mytuner.mobi\/media\/radios\/g4ebsjvhpaua.png","url":"http:\/\/radio11.plathong.net:8400\/;?type=http?1536326009750.mp3"},{"name":"สถานีวิทุยส่วนภูมิภาค MCOT Radio นครราชสีมา","logo":"http:\/\/static.mytuner.mobi\/media\/radios\/sgdyqwwmjgyw.png","url":"http:\/\/rstream.mcot.net:9048\/;.mp3"},{"name":"สถานีวิทุยส่วนภูมิภาค MCOT Radio อุดรธานี","logo":"http:\/\/static.mytuner.mobi\/media\/radios\/wgmx8v9mcect.png","url":"http:\/\/rstream.mcot.net:9044\/;.mp3"},{"name":"Pleng4load.com","logo":"http:\/\/static.mytuner.mobi\/media\/radios\/b7cl42qng9kj.png","url":"https:\/\/radio14.plathong.net\/7002\/;stream.mp3"},{"name":"Eazy FM 105.5","logo":"http:\/\/static.mytuner.mobi\/media\/radios\/M5t3aG2vcB.png","category":"Easy Listening","url":"https:\/\/wzedge1.becteroradio.com\/Eazy\/Eazy-Listen-Med\/playlist.m3u8"},{"name":"Radio Trip Phuket","logo":"http:\/\/static.mytuner.mobi\/media\/radios\/tvyx8atdvrpn.png","url":"http:\/\/103.58.149.186:1150\/;stream\/"},{"name":"เพลงลูกทุ่ง Huahin Radio","logo":"http:\/\/static.mytuner.mobi\/media\/radios\/ddqtw2szlcdc.png","url":"https:\/\/inter1.plathong.net\/7008\/;stream.mp3?type=http"},{"name":"FM ONE 103.5","logo":"http:\/\/static.mytuner.mobi\/media\/radios\/hadgyexuzma9.png","category":"Variety","url":"http:\/\/get1025.plathong.net:7010\/;"},{"name":"สถานีวิทุยส่วนภูมิภาค MCOT Radio สงขลา","logo":"http:\/\/static.mytuner.mobi\/media\/radios\/bjqbf5jyr9eb.png","url":"http:\/\/rstream.mcot.net:9104\/;.mp3"},{"name":"American Top 40","logo":"http:\/\/static.mytuner.mobi\/media\/radios\/K5VfKFaArk.jpeg","url":"http:\/\/streaming.radionomy.com\/AMERICANTOP40"},{"name":"Modern Radio Tak","logo":"http:\/\/static.mytuner.mobi\/media\/radios\/uunmnkfuxvjt.jpg","url":"http:\/\/rstream.mcot.net:9076\/;"},{"name":"สถานีวิทุยส่วนภูมิภาค MCOT Radio สุราษฎร์ธานี","logo":"http:\/\/static.mytuner.mobi\/media\/radios\/fuuyh6hfkzpb.png","url":"http:\/\/rstream.mcot.net:9090\/;.mp3"},{"name":"สถานีวิทุยส่วนภูมิภาค MCOT Radio สิงห์บุรี","logo":"http:\/\/static.mytuner.mobi\/media\/radios\/mwxp7szpu3jy.png","url":"http:\/\/rstream.mcot.net:9006\/;.mp3"},{"name":"102 Radio สถานีวิทยุกระจายเสียง ขส.ทบ","logo":"http:\/\/static.mytuner.mobi\/media\/radios\/kD8W96emy7.jpg","category":"Variety","url":"http:\/\/media.login.in.th:1100\/;stream.mp3"},{"name":"Modern Radio Chanthaburi","logo":"http:\/\/static.mytuner.mobi\/media\/radios\/jsgn8wcymtby.jpg","url":"http:\/\/rstream.mcot.net:9020\/;.mp3"},{"name":"Wat-Nairong","logo":"http:\/\/static.mytuner.mobi\/media\/radios\/5bghktcqn7mt.png","url":"http:\/\/103.7.56.219:4106"},{"name":"103 Like FM","logo":"http:\/\/static.mytuner.mobi\/media\/radios\/gLFBxhmDEk.jpg","url":"http:\/\/103radio.cdnth.com\/radio\/likefm\/icecast.audio"},{"name":"สถานีวิทุยส่วนภูมิภาค MCOT Radio พิษณุโลก","logo":"http:\/\/static.mytuner.mobi\/media\/radios\/jwashab4fshe.png","url":"http:\/\/rstream.mcot.net:9078\/;.mp3"},{"name":"คลื่นเพื่อนร่วมทาง AM 1143","logo":"http:\/\/static.mytuner.mobi\/media\/radios\/ApvP3yAZEE.png","url":"http:\/\/rstream.mcot.net:8000\/am1143"},{"name":"สถานีวิทุยส่วนภูมิภาค MCOT Radio นครศรีธรรมราช","logo":"http:\/\/static.mytuner.mobi\/media\/radios\/vm4z3fhmyesb.png","url":"http:\/\/rstream.mcot.net:9094\/;.mp3"},{"name":"สถานีวิทุยส่วนภูมิภาค MCOT Radio แพร่","logo":"http:\/\/static.mytuner.mobi\/media\/radios\/nkhm54zwyhva.png","url":"http:\/\/rstream.mcot.net:9070\/;.mp3"},{"name":"Muanglungradio","logo":"http:\/\/static.mytuner.mobi\/media\/radios\/edjaw8cuvmey.png","url":"http:\/\/radio12.plathong.net:7076\/"},{"name":"iloveradio","logo":"http:\/\/static.mytuner.mobi\/media\/radios\/TWPLguZASY.png","url":"http:\/\/stream03.iloveradio.de\/iloveradio1.mp3"},{"name":"Rock On Radio","logo":"http:\/\/static.mytuner.mobi\/media\/radios\/u4fkg5wjjdgf.png","url":"https:\/\/wzedge1.becteroradio.com\/Rock\/Rock-Listen-Med\/playlist.m3u8"},{"name":"Hits and Fun","logo":"http:\/\/static.mytuner.mobi\/media\/radios\/p5db7WFZgY.jpg","url":"http:\/\/ns2.hitsandfun.net\/hitsandfun-hd?1447949076565.mp3"},{"name":"Green Wave 106.5 FM","logo":"http:\/\/static.mytuner.mobi\/media\/radios\/52kDndQrUz.jpg","category":"Adult Contemporary","url":"https:\/\/real4.atimemedia.com\/green"},{"name":"สถานีวิทุยส่วนภูมิภาค MCOT Radio มหาสารคาม","logo":"http:\/\/static.mytuner.mobi\/media\/radios\/nk5nuhrjtg9h.png","url":"http:\/\/rstream.mcot.net:9034\/;.mp3"},{"name":"เพลงลูกทุ่ง Looktung Eingdoi Station","logo":"http:\/\/static.mytuner.mobi\/media\/radios\/eln9tfyqce5h.jpg","category":"90s","url":"http:\/\/inter1.plathong.net\/7034\/;"},{"name":"FM 92.7 Monkong","logo":"http:\/\/static.mytuner.mobi\/media\/radios\/22mc5vfaexac.jpg","url":"http:\/\/103.22.182.105:7254\/"},{"name":"106.2 OnAirPlus","logo":"http:\/\/static.mytuner.mobi\/media\/radios\/j6aujxwnewgq.jpg","category":"Hot AC","url":"http:\/\/link.onair.network:8052\/stream.mp3"},{"name":"BBC World Service","logo":"http:\/\/static.mytuner.mobi\/media\/radios\/Lz9bbsba4c.png","category":"News","url":"http:\/\/bbcwssc.ic.llnwd.net\/stream\/bbcwssc_mp1_ws-eieuk_backup"},{"name":"Musichitz Radio Inter","logo":"http:\/\/static.mytuner.mobi\/media\/radios\/2ercevqaw4vk.png","url":"http:\/\/112.121.150.133:8006\/stream"},{"name":"สถานีวิทุยส่วนภูมิภาค MCOT Radio เลย","logo":"http:\/\/static.mytuner.mobi\/media\/radios\/2xrr2hjvqjkk.png","url":"http:\/\/rstream.mcot.net:9038\/;.mp3"},{"name":"สถานีวิทุยส่วนภูมิภาค MCOT Radio ชลบุรี","logo":"http:\/\/static.mytuner.mobi\/media\/radios\/gkbxex6pppq9.png","url":"http:\/\/rstream.mcot.net:9022\/;.mp3"},{"name":"Thai Weather Radio AM 1287","logo":"http:\/\/static.mytuner.mobi\/media\/radios\/5pb4mrtl46ca.png","url":"http:\/\/www.radio.tmd.go.th:8014\/;streem.mp3"},{"name":"สถานีวิทุยส่วนภูมิภาค MCOT Radio อุตรดิตถ์","logo":"http:\/\/static.mytuner.mobi\/media\/radios\/eduaa39sp9kj.png","url":"http:\/\/rstream.mcot.net:9082\/;.mp3"},{"name":"บ่าวเซียงป่องเรดิโอ(ปลาทอง)","logo":"http:\/\/static.mytuner.mobi\/media\/radios\/nfjz3hy6qwlz.png","url":"http:\/\/103.22.182.105:7116\/"},{"name":"เพื่อชีวิต request radio","logo":"http:\/\/static.mytuner.mobi\/media\/radios\/RKj5SekkUY.png","url":"http:\/\/27.254.142.208:8300\/"},{"name":"FM89 I am radio - Lop Buri","logo":"http:\/\/static.mytuner.mobi\/media\/radios\/ndqpbja6pjrp.jpg","category":"Adult Contemporary","url":"http:\/\/link.onair.network:8054\/stream"},{"name":"Mono Fresh FM","logo":"http:\/\/static.mytuner.mobi\/media\/radios\/ymxm7whuvkph.jpeg","url":"http:\/\/stream.monofresh915.com:8000\/Radio_fresz915FM.mp3"},{"name":"สถานีวิทุยส่วนภูมิภาค MCOT Radio อุทัยธานี","logo":"http:\/\/static.mytuner.mobi\/media\/radios\/dcbnpjhkerbh.png","url":"http:\/\/rstream.mcot.net:9008\/;.mp3"},{"name":"Musichitz Radio Pop","logo":"http:\/\/static.mytuner.mobi\/media\/radios\/lwteyumhsccx.png","url":"http:\/\/112.121.150.133:8122\/stream"},{"name":"ลูกทุ่งใหม่ 88.5 Wow Radio จังหวัดแพร่","logo":"http:\/\/static.mytuner.mobi\/media\/radios\/dfnz77afruzv.jpg","category":"Hindi","url":"http:\/\/ohmi-design.com:8870\/\/"},{"name":"สถานีวิทุยส่วนภูมิภาค MCOT Radio น่าน","logo":"http:\/\/static.mytuner.mobi\/media\/radios\/ucqmhgj5wf62.png","url":"http:\/\/rstream.mcot.net:9072\/;.mp3"},{"name":"COOL Fahrenheit 93","logo":"http:\/\/static.mytuner.mobi\/media\/radios\/KvDHAwT62s.png","category":"Easy Listening","url":"http:\/\/111.223.51.7:8100\/;"},{"name":"FM102 คลื่นคนทำงาน","logo":"http:\/\/static.mytuner.mobi\/media\/radios\/rvk9j5ak7cqs.jpeg","url":"http:\/\/media.login.in.th:1100\/;stream.mp3?1487175593832"},{"name":"Friends Bangkok","logo":"http:\/\/static.mytuner.mobi\/media\/radios\/c34s7h6nxg6t.png","category":"Adult Contemporary","url":"http:\/\/210.1.60.244:8000\/FriendsBangkok"},{"name":"Met 107 FM","logo":"http:\/\/static.mytuner.mobi\/media\/radios\/rf6jXen9zU.jpg","category":"Talk","url":"https:\/\/mcotdigital-w9rpgl.cdn.byteark.com\/radiocdn_edge\/fm107.stream_aac\/playlist.m3u8"},{"name":"Numberone Station","logo":"http:\/\/static.mytuner.mobi\/media\/radios\/mflt6dw9cagx.png","category":"Adult Contemporary","url":"http:\/\/112.121.151.133:8160\/live"},{"name":"เพลงลูกกรุง LookkungRadio Eingdoi Station","logo":"http:\/\/static.mytuner.mobi\/media\/radios\/ykdw83n7gmqj.jpg","category":"Classic Hits","url":"http:\/\/ohmi-design.com:8708\/;"},{"name":"GeezzMAX Radio Society","logo":"http:\/\/static.mytuner.mobi\/media\/radios\/ryhhx3h7x6tf.png","url":"http:\/\/103.22.182.105:7300\/"},{"name":"สวพ fm 91","logo":"http:\/\/static.mytuner.mobi\/media\/radios\/ptshgz8bvtsk.jpeg","url":"http:\/\/122.155.16.48:8955\/;stream.mp3"},{"name":"COOL 93 Fahrenheit","logo":"http:\/\/api.radiosworld.info\/files\/radio\/logo\/3175e5cd4583233d4c6aa03fee429a4bffbd8125.jpeg","category":"News","url":"http:\/\/111.223.51.7:8000\/"},{"name":"COOL fahrenheit 93","logo":"http:\/\/api.radiosworld.info\/files\/radio\/logo\/f35984ec466c8bb58f4c0ab61db45f64673652c1.jpeg","category":"News","url":"http:\/\/111.223.51.7:8005\/"},{"name":"FM One","logo":"http:\/\/api.radiosworld.info\/files\/radio\/logo\/fc92b7d7e127eca59c09bb1cfbf396db961a5be9.jpeg","category":"News","url":"http:\/\/fmone.plathong.net:7010\/;stream.mp3"},{"name":"COOL celsius 91.5","logo":"http:\/\/api.radiosworld.info\/files\/radio\/logo\/587c25d7a866f6ebabd26a72a569fdd59c9fa553.jpeg","category":"News","url":"http:\/\/111.223.51.7:8100\/"},{"name":"Thai Muslim Radio","logo":"http:\/\/api.radiosworld.info\/files\/radio\/logo\/4d28345b5431cb9c21177cda19957362321cd260.jpeg","category":"News","url":"http:\/\/radio.portradiothai.com:6030\/;"},{"name":"107.75 MHZ Pattaya Sunshine","logo":"https:\/\/static.wixstatic.com\/media\/a72f3a_d1932809a39f43c6b3376d1f6f9bb1b2~mv2.png?dn=r28366.png","category":"","url":"http:\/\/icecast.piesoft.net:8000\/pat?type=.mp3\/;stream.mp3"},{"name":"Adventist Internet Radio","logo":"https:\/\/static.wixstatic.com\/media\/a72f3a_0be4697a0d214aa5bab523ff490a789d~mv2.png?dn=r28368.png","category":"","url":"http:\/\/streaming.radionomy.com\/AdventistInternetRadio?type=.mp3\/;stream.mp3"},{"name":"Capitol FM Bangkok","logo":"https:\/\/static.wixstatic.com\/media\/a72f3a_b55c1cea8496438eab203878471d28d8~mv2.png?dn=r28372.png","category":"","url":"http:\/\/atlanticthai.primcast.com:5898\/;stream.mp3"},{"name":"Hip Radio","logo":"https:\/\/static.wixstatic.com\/media\/a72f3a_493ff254b7d345c8995ae34fd77d1a86~mv2.png?dn=r28384.png","category":"","url":"http:\/\/5.79.86.161:8800\/;stream.mp3"},{"name":"OK Click Station","logo":"https:\/\/static.wixstatic.com\/media\/a72f3a_381062b0ea5e46ac989555996cadb7a3~mv2.png?dn=r32109.png","category":"","url":"http:\/\/media.login.in.th:1630\/"},{"name":"Modern Radio Narathiwat","logo":"https:\/\/static.wixstatic.com\/media\/a72f3a_2b45c9835ef84718a8e8d611ea715e0f~mv2.png?dn=r32131.png","category":"","url":"http:\/\/live.smiledj.net:8214\/audio"},{"name":"Radio Trip Phuket","logo":"https:\/\/static.wixstatic.com\/media\/a72f3a_490f94f9d0ee41ae9279c6b99752da36~mv2.png?dn=r32135.png","category":"","url":"http:\/\/media.login.in.th:1150"},{"name":"LIVE 89.5","logo":"https:\/\/static.wixstatic.com\/media\/a72f3a_7c4ddc85c38c46ff99a7e095204e8bec~mv2.png?dn=r28387.png","category":"","url":"http:\/\/myradio.plathong.net:8020\/;stream.mp3"},{"name":"Munfm 104.75","logo":"https:\/\/static.wixstatic.com\/media\/a72f3a_94f621a7f77e40828a832a8eb7d4d55e~mv2.png?dn=r28392.png","category":"","url":"http:\/\/103.246.18.3:4018\/;stream.mp3"},{"name":"Voice of navy 5 Pattaya","logo":"https:\/\/static.wixstatic.com\/media\/a72f3a_72aac3ef396645f0935994e323cd7b7f~mv2.png?dn=r28407.png","category":"","url":"http:\/\/myradio.plathong.net:8704\/;stream.mp3"},{"name":"Manager Radio","logo":"https:\/\/static.wixstatic.com\/media\/a72f3a_652aaec726b94528aea41f7ad214e342~mv2.png?dn=r16613.png","category":"","url":"http:\/\/202.142.203.23:1935\/RadioStream1\/radio.stream\/playlist.m3u8"},{"name":"EFM 104.5","logo":"http:\/\/static.mytuner.mobi\/media\/radios\/Ck8sVEmWdv.jpg","category":"All","url":"http:\/\/real4.atimemedia.com\/efm"},{"name":"103 Like FM","logo":"http:\/\/static.mytuner.mobi\/media\/radios\/gLFBxhmDEk.jpg","category":"All","url":"http:\/\/103.22.182.105:7054\/"},{"name":"เพลงลูกทุ่ง Huahin Radio","logo":"http:\/\/static.mytuner.mobi\/media\/radios\/ddqtw2szlcdc.png","category":"All","url":"https:\/\/inter1.plathong.net\/7008\/;"},{"name":"City Radio Pattaya","logo":"http:\/\/static.mytuner.mobi\/media\/radios\/vBjbAq89jv.jpg","category":"All","url":"http:\/\/onair.onair.network:8074"},{"name":"ipmusic","logo":"http:\/\/static.mytuner.mobi\/media\/radios\/jgYrth4Nt9.jpg","category":"All","url":"http:\/\/live9.avf.ch:8000\/ipmusic256"},{"name":"93.5 Happy Time","logo":"http:\/\/static.mytuner.mobi\/media\/radios\/nns72bppeakv.png","category":"All","url":"http:\/\/122.155.9.34:8000\/;stream.mp3"},{"name":"Sawasdee106.2","logo":"","url":"http:\/\/radio11.plathong.net:7002\/"},{"name":"Sumrit radio","logo":"","url":"http:\/\/103.22.182.105:7072\/"},{"name":"999radio","logo":"","url":"http:\/\/103.22.182.153:8344\/"},{"name":"Xansiam","logo":"","url":"http:\/\/radio12.plathong.net:8480\/"},{"name":"IKyzaa Radio","logo":"null","category":"Acid Jazz","url":"http:\/\/stream.pjcdn.com:9000\/;?_=0.7879893589600064"},{"name":"Sunshine Radio","logo":"","category":"Acid Jazz","url":"http:\/\/icecast.piesoft.net:8000\/pat128"},{"name":"Radio Thailand \/ AM 891","logo":"","category":"News","url":"http:\/\/prdonline.prd.go.th:8202\/"},{"name":"City Radio Pattaya","logo":"","category":"News","url":"http:\/\/onair22.onair.network:8074\/stream\/3\/;"},{"name":"Phuket Live Radio 89.5","logo":"null","category":"Acoustic","url":"http:\/\/myradio.plathong.net:8020\/;"},{"name":"Radio Thailand Chiangmai","logo":"","category":"Alternative","url":"http:\/\/202.129.35.2:8008\/"},{"name":"R Thailand 88.0","logo":"","category":"Acid Jazz","url":"http:\/\/prdonline.prd.go.th:8200\/"},{"name":"Greetz 102.5 MHz","logo":"null","category":"Acid Jazz","url":"http:\/\/radio4.thzhost.com:8510\/;"},{"name":"IC Radio Ayutthaya","logo":"null","category":"Art","url":"http:\/\/radio1.serverradio.net:8278\/;"},{"name":"Buddy Radio 104.5 FM","logo":"","category":"Acid Jazz","url":"http:\/\/radio14.plathong.net:7036\/stream\/1\/"},{"name":"MCOT Seed 97.5 FM","logo":"","category":"News","url":"http:\/\/rstream.mcot.net:8000\/fm975"},{"name":"Buddy Radio FM 104.5","logo":"null","category":"Acoustic","url":"http:\/\/radio14.plathong.net:7036\/;"},{"name":"DJ DOMINATION REMIX RADIO","logo":"null","category":"English","url":"http:\/\/radio1.serv4biz.com:49201\/stream\/1\/"},{"name":"Vipak Radio","logo":"null","category":"Song","url":"http:\/\/103.22.182.16:7066\/;"},{"name":"PassionFM Exclusive Channel \/ 97 Tourist Station","logo":"null","category":"Active Rock","url":"http:\/\/link.onair.network:8058\/;"},{"name":"Phuket Island Radio","logo":"null","category":"90","url":"http:\/\/stream.phuketfmradio.com\/pfmAAC64"},{"name":"Request Radio","logo":"null","category":"80","url":"http:\/\/27.254.142.208:8100\/;?1436380774785.mp3"},{"name":"99.25 Maitrichit","logo":"","category":"Afro-Beat","url":"http:\/\/live.smiledj.net:8082\/audio"},{"name":"Radio Trip Phuket 89.75","logo":"null","category":"Comedy","url":"http:\/\/media.login.in.th:1150\/;"},{"name":"Radio Thailand 918 AM","logo":"","category":"Ambient","url":"http:\/\/prdonline.prd.go.th:8218\/"},{"name":"MJU RADIO \/ Maejo University Station","logo":"null","category":"Ambient","url":"http:\/\/112.121.150.133:8282\/"},{"name":"Radio Thailand Phetchabun","logo":"","category":"Ambient","url":"http:\/\/prdonline.prd.go.th:8212\/"},{"name":"UB Radio","logo":"","category":"Acid Jazz","url":"http:\/\/centova.ubradio.net:8300\/autodj"},{"name":"Capitol.fm","logo":"null","category":"60 years","url":"http:\/\/atlanticthai.primcast.com:5898\/;"},{"name":"WatPakBo","logo":"null","category":"News","url":"http:\/\/radio1.siamlivehost.com:8001\/;"},{"name":"BaKaWorld Anime Radio Online 24 HR","logo":"null","category":"New Wave","url":"http:\/\/144.217.203.184:8398\/stream"},{"name":"GF Radio","logo":"null","category":"English","url":"http:\/\/www2.gfcom.info:8000\/"},{"name":"Adventist Internet Radio","logo":"null","category":"Soundtracks for films","url":"http:\/\/streaming.radionomy.com\/JamendoLounge"},{"name":"Buzzin Radio Pattaya","logo":"null","category":"Soundtracks for films","url":"http:\/\/streams.radio.co\/s102cd33bc\/listen"},{"name":"Wink.in.th","logo":"null","category":"","url":"http:\/\/radio.wink.in.th:80\/"},{"name":"Pattaya People Radio","logo":"null","category":"Ambient","url":"http:\/\/s1.thailandstreaming.net:8020\/yes2day.mp3"},{"name":"หวย","logo":"null","category":"","url":"http:\/\/prdonline.prd.go.th:8216\/;stream.mp3"},{"name":"99 Active Radio","logo":"","category":"","url":"http:\/\/mcotdigital-gvwieh.cdn.byteark.com\/radiocdn_edge\/fm99.stream_aac\/playlist.m3u8"},{"name":"CityLife 93.75","logo":"","category":"","url":"http:\/\/onair.onair.network:8076\/1"},{"name":"Cool 93 Fahrenheit","logo":"","category":"","url":"http:\/\/111.223.51.7:8000"},{"name":"CU Radio 101.5 MHz","logo":"","category":"","url":"http:\/\/161.200.134.32:1935\/live\/liveradio128\/playlist.m3u8"},{"name":"DMC.TV","logo":"","category":"","url":"http:\/\/dmc072.net:443"},{"name":"Eingdoi Radio Thailand","logo":"","category":"","url":"http:\/\/ohmi-design.com:8170"},{"name":"Number One Radio 103.5FM","logo":"","category":"","url":"http:\/\/str04.fluidstream.net\/rn1.mp3"},{"name":"ondio.in","logo":"","category":"","url":"http:\/\/112.121.150.133:8024\/stream"},{"name":"Pophits Radio Eingdoi","logo":"","category":"","url":"http:\/\/ohmi-design.com:9090"},{"name":"UB Radio","logo":"","category":"","url":"http:\/\/centova.ubradio.net:8300\/stream"},{"name":"Wink Radio","logo":"","category":"","url":"http:\/\/radio.wink.in.th"},{"name":"Wow Radio Thailand","logo":"","category":"","url":"http:\/\/ohmi-design.com:8870"},{"name":"ลูกทุ่งกรุงธน","logo":"","category":"","url":"http:\/\/rcp.plathong.net:7154\/"},{"name":"เพลงลูกทุ่ง Looktung Eingdoi Station","logo":"","category":"","url":"http:\/\/inter1.plathong.net\/7034\/;stream\/1"},{"name":"​ เพลงลูกกรุง LookkungRadio Eingdoi Station Thailand","logo":"","category":"","url":"http:\/\/ohmi-design.com:8708"},{"name":"107 Lovefm feelgood | Internet Only | Variety","logo":"","url":"http:\/\/103.22.182.105:7296"},{"name":"88.5 Wow Radio Phrae | Internet Only | Pop|Top|40","logo":"","url":"http:\/\/ohmi-design.com:8870\/;"},{"name":"90 Rak Thai | Bangkok | World Asia","logo":"","url":"http:\/\/radio11.plathong.net:8896\/stream"},{"name":"Bangkok.fm Thailand | Bangkok | Top 40","logo":"","url":"http:\/\/62.210.10.4:8644\/stream\/1\/"},{"name":"Buddy Radio 104.5 | Bangkok | World Asia","logo":"","url":"http:\/\/radio14.plathong.net:7036\/"},{"name":"Critical BaKaRadio | Internet Only | Soundtracks","logo":"","url":"http:\/\/144.217.203.184:8398\/mountpoint"},{"name":"DMC TV Thai | Internet Only | Religious","logo":"","url":"http:\/\/dmc072.net:443\/"},{"name":"Eingdoi Radio Thailand | Bangkok | Indie|Pop|Rock|Top 40","logo":"","url":"http:\/\/ohmi-design.com:8170\/stream\/1\/"},{"name":"Fabulous 103 FM | Pattaya | Variety","logo":"","url":"http:\/\/thai-host.com:8100\/pattaya103d"},{"name":"Family Radio 107.50 | Nonthaburi | World Asia","logo":"","url":"http:\/\/radio14.plathong.net\/7298\/"},{"name":"FM One 103.5 FM | Bangkok | Pop","logo":"","url":"http:\/\/fmone.plathong.net:7010"},{"name":"Get Radio 102.5 FM | Bangkok | Pop","logo":"","url":"http:\/\/get1025.plathong.net:7004\/"},{"name":"GF Radio | Internet Only | Anime","logo":"","url":"http:\/\/www.gfcom.info:8000\/;"},{"name":"Happy Radio 98.5FM | Internet Only | Pop|Adult Contemporary","logo":"","url":"http:\/\/202.129.206.117:9037\/;"},{"name":"Happy Time | Internet Only | Pop","logo":"","url":"http:\/\/radio99.servradio.com:9336\/;"},{"name":"HITSTATION RADIO THAILAND | Internet Only | Variety","logo":"","url":"http:\/\/103.22.182.29:7016"},{"name":"HITZ FM Exclusive 102.25 MHz | Internet Only | Variety","logo":"","url":"http:\/\/103.22.182.105:7292"},{"name":"Hot 107 FM Pattaya | Internet Only | Hip Hop","logo":"","url":"http:\/\/s2.radio.co:80\/s48c37aefb\/listen"},{"name":"Huahin Radio Thailand | Bangkok | Pop|Rock|Top 40","logo":"","url":"http:\/\/inter1.plathong.net\/7008\/stream\/1\/"},{"name":"I Am 89FM | Lop Buri | World Asia","logo":"","url":"http:\/\/link.onair.network:8054\/"},{"name":"Isantumhome Radio | Bangkok | World Asia","logo":"","url":"http:\/\/radio2.serverradio.net:8444\/"},{"name":"Islamic Radio Thailand | Internet Only | Islamic","logo":"","url":"http:\/\/184.173.185.71:9934"},{"name":"Kiss FM | Internet Only | Adult Contemporary","logo":"","url":"http:\/\/s1.thailandstreaming.net:8020\/;stream.nsv"},{"name":"Lafayette Radio | Internet Only | Jazz","logo":"","url":"http:\/\/18193.live.streamtheworld.com\/SAM05AAC287_SC"},{"name":"Live 89.5 | Phuket | Pop","logo":"","url":"http:\/\/myradio.plathong.net:8020\/"},{"name":"LookkungRadio Eingdoi Station Thailand | Bangkok | Indie|Pop|Rock|Top 40","logo":"","url":"http:\/\/ohmi-design.com:8708\/stream\/1\/"},{"name":"Looktung Eingdoi Station Thailand | Bangkok | Indie|Pop|Rock|Top 40","logo":"","url":"http:\/\/inter1.plathong.net\/7034\/stream\/1\/"},{"name":"Mazz Radio 107.75 | Phuket | Pop","logo":"","url":"http:\/\/radio1.comgig.com:4096\/"},{"name":"MCOT Chaiyaphum 102.0 FM | Chaiyaphum | Public","logo":"","url":"http:\/\/rstream.mcot.net:9046\/"},{"name":"MCOT Chantaburee 95.25 | Chantaburi | World Asia","logo":"","url":"http:\/\/rstream.mcot.net:9020"},{"name":"MCOT ChiangRai 101.25 FM | Chiang Rai | World Asia|Dance","logo":"","url":"http:\/\/rstream.mcot.net:9060\/"},{"name":"MCOT Chonburi | Bangkok | Hits","logo":"","url":"http:\/\/rstream.mcot.net:9022\/"},{"name":"MCOT Chumphon 90.75 FM | Chumphon | World Asia","logo":"","url":"http:\/\/rstream.mcot.net:9014"},{"name":"MCOT Kalasin 92.0 FM | Kalasin | World Asia","logo":"","url":"http:\/\/rstream.mcot.net:9028"},{"name":"MCOT Kamphaeng Phet 92.7 FM | Kamphaeng Phet | Public","logo":"","url":"http:\/\/rstream.mcot.net:9002\/"},{"name":"MCOT Karnchanaburi 107.2 FM | Kanchanaburi | Public","logo":"","url":"http:\/\/rstream.mcot.net:9010\/"},{"name":"MCOT Khonkhen | Bangkok | Hits","logo":"","url":"http:\/\/rstream.mcot.net:9030\/"},{"name":"MCOT Krabi 105 FM | Krabi | World Asia","logo":"","url":"http:\/\/rstream.mcot.net:9084\/"},{"name":"MCOT Lampang 99.0 FM | Lampang | Public","logo":"","url":"http:\/\/rstream.mcot.net:9074\/"},{"name":"MCOT Lamphun 96.5 FM | Lamphun | World Asia","logo":"","url":"http:\/\/rstream.mcot.net:9068\/"},{"name":"MCOT Loei 100 FM | Loei | Public","logo":"","url":"http:\/\/rstream.mcot.net:9038\/"},{"name":"MCOT Maehongson 99.5 FM | Mae Hong Son | World Asia","logo":"","url":"http:\/\/rstream.mcot.net:9064"},{"name":"MCOT Mahasarakham 100.5 FM | Borabu | Public","logo":"","url":"http:\/\/rstream.mcot.net:9034"},{"name":"MCOT Modern Radio Langsuan 104.75 FM | Lang Suan | World Asia","logo":"","url":"http:\/\/rstream.mcot.net:9018\/"},{"name":"MCOT Nakhon Ratchasima 95.7 FM | Nakhon Ratchasima | Public","logo":"","url":"http:\/\/rstream.mcot.net:9048\/"},{"name":"MCOT Nakhon Si Thammarat 104.5 FM | Nakhon Si Thammarat | Public","logo":"","url":"http:\/\/rstream.mcot.net:9094"},{"name":"MCOT Nakhonphanom 93.5 FM | Nakhon Phanom | Public","logo":"","url":"http:\/\/rstream.mcot.net:9032\/"},{"name":"MCOT Nan 92 FM | Nan | World Asia","logo":"","url":"http:\/\/rstream.mcot.net:9072\/"},{"name":"MCOT Narathiwat 96.0 FM | Narathiwat | Public","logo":"","url":"http:\/\/rstream.mcot.net:9096"},{"name":"MCOT Pattani 91.0 FM | Pattani | Public","logo":"","url":"http:\/\/rstream.mcot.net:9098\/"},{"name":"MCOT Phangha | Bangkok | Hits","logo":"","url":"http:\/\/rstream.mcot.net:9086\/"},{"name":"MCOT Phatthalung 95.75 FM | Phatthalung | World Asia","logo":"","url":"http:\/\/rstream.mcot.net:9100\/"},{"name":"MCOT Phayao 97.25 FM | Phayao | World Asia","logo":"","url":"http:\/\/rstream.mcot.net:9062\/"},{"name":"MCOT Phichit 107.7 FM | Phichit | Public","logo":"","url":"http:\/\/rstream.mcot.net:9004"},{"name":"MCOT Phitsanulok 106.25 FM | Phitsanulok | World Asia","logo":"","url":"http:\/\/rstream.mcot.net:9078\/"},{"name":"MCOT Phuket | Bangkok | Hits","logo":"","url":"http:\/\/rstream.mcot.net:9088\/"},{"name":"MCOT Prachuap Khiri Khan 106.7 FM | Prachuap Khiri Khan | Public","logo":"","url":"http:\/\/rstream.mcot.net:9012\/"},{"name":"MCOT Prae 93.0 FM | Prae | World Asia","logo":"","url":"http:\/\/rstream.mcot.net:9070\/"},{"name":"MCOT Ranong 100.5 FM | Ranong | World Asia","logo":"","url":"http:\/\/rstream.mcot.net:9016\/"},{"name":"MCOT Rayong 96.7 FM | Rayong | Public","logo":"","url":"http:\/\/rstream.mcot.net:9026\/"},{"name":"MCOT Roi Et 101.0 FM | Roi Et | Public","logo":"","url":"http:\/\/rstream.mcot.net:9036\/"},{"name":"MCOT Sakonnakhon 107 FM | Sakhon Nakhon | Public","logo":"","url":"http:\/\/rstream.mcot.net:9040"},{"name":"MCOT Satun 93.2 FM | Satun | Public","logo":"","url":"http:\/\/rstream.mcot.net:9106\/"},{"name":"MCOT Sing Buri 105.3 FM | Sing Buri | Public","logo":"","url":"http:\/\/rstream.mcot.net:9006\/"},{"name":"MCOT Sisaket 95.0 FM | Si Sa Ket | Public","logo":"","url":"http:\/\/rstream.mcot.net:9054"},{"name":"MCOT Songkhla | Bangkok | Hits","logo":"","url":"http:\/\/rstream.mcot.net:9104\/"},{"name":"MCOT Sukhothai | Bangkok | Hits","logo":"","url":"http:\/\/rstream.mcot.net:9080\/"},{"name":"MCOT Surat Thani 102.0 FM | Surat Thani | World Asia","logo":"","url":"http:\/\/rstream.mcot.net:9090\/"},{"name":"MCOT Surin | Bangkok | Hits","logo":"","url":"http:\/\/rstream.mcot.net:9056\/"},{"name":"MCOT Tak 97.2 FM | Tak | Public","logo":"","url":"http:\/\/rstream.mcot.net:9076\/"},{"name":"MCOT Trang 106.2 FM | Trang | World Asia","logo":"","url":"http:\/\/rstream.mcot.net:9092\/"},{"name":"MCOT Trat 107.25 FM | Trat | World Asia","logo":"","url":"http:\/\/rstream.mcot.net:9024"},{"name":"MCOT Ubonratchathani 107 FM | Ubonratchathani | World Asia","logo":"","url":"http:\/\/rstream.mcot.net:9058"},{"name":"MCOT Udonthanee | Bangkok | Hits","logo":"","url":"http:\/\/rstream.mcot.net:9044\/"},{"name":"MCOT Uthai Thani 107.75 FM | Uthai Thani | World Asia","logo":"","url":"http:\/\/rstream.mcot.net:9008\/"},{"name":"MCOT Uttaradit 98.5 FM | Uttaradit | Public","logo":"","url":"http:\/\/rstream.mcot.net:9082"},{"name":"MCOT Yala 102.5 FM | Bangkok | News","logo":"","url":"http:\/\/rstream.mcot.net:9102"},{"name":"MCOT Yasothon 95.25 FM | Internet Only | World Asia","logo":"","url":"http:\/\/rstream.mcot.net:9052"},{"name":"Mercigod Radio | Internet Only | Pop|Top40","logo":"","url":"http:\/\/122.155.0.201:9000\/;stream.mp3"},{"name":"Music Library Thailand | Internet Only | Variety","logo":"","url":"http:\/\/112.121.150.133:9114"},{"name":"Muslim Thai Radio | Internet Only | Religious","logo":"","url":"http:\/\/radio.portradiothai.com:6026"},{"name":"Phuket Radio 91.5 | Phuket | Variety","logo":"","url":"http:\/\/stream.phuketfmradio.com:8000\/pfmMP3"},{"name":"Pong Pan Radio 101.75 | Bangkok | World Asia","logo":"","url":"http:\/\/radio.portradiothai.com:6010\/"},{"name":"PRD RadioThailand | Internet Only | Talk|Hits|Country|Rock|Classic|Bluegrass","logo":"","url":"http:\/\/118.175.16.69:8216\/;"},{"name":"Quran Thai Islam Radio 104.25 FM | Bangkok | Religious","logo":"","url":"http:\/\/radio.portradiothai.com:6030\/"},{"name":"Radio Chiangmai 93.25 FM | Chiangmai | News|Talk|Variety","logo":"","url":"http:\/\/prdonline.prd.go.th:8118\/;"},{"name":"Radio Chiangmai FM. 98.0 | Chiang Mai | Public|World Asia","logo":"","url":"http:\/\/prdonline.prd.go.th:8120\/"},{"name":"Radio Thailand 97.0 | Bangkok | News","logo":"","url":"http:\/\/prdonline.prd.go.th:8208\/"},{"name":"Radio Thailand AM 918 | Bangkok | World Asia","logo":"","url":"http:\/\/118.175.16.69:8218\/"},{"name":"Radio Thailand FM 92.5 | Bangkok | Talk","logo":"","url":"http:\/\/prdonline.prd.go.th:8202\/;"},{"name":"Radio Thailand FM 95.5 | Bangkok | Top 40","logo":"","url":"http:\/\/prdonline.prd.go.th:8206\/"},{"name":"Radio Thailand","logo":"","url":"http:\/\/prd5online.prd.go.th:9110"},{"name":"Radio Thailand","logo":"","url":"http:\/\/prd5online.prd.go.th:9060"},{"name":"Radio Trip Phuket 89.75 | Internet Only | Adult Contemporary","logo":"","url":"http:\/\/media.login.in.th:1150\/;stream.nsv"},{"name":"Samui Island Radio Stream | Samui | Pop|Rock","logo":"","url":"http:\/\/78.129.159.25:8195\/stream"},{"name":"Samyod Bangkok Radio 1179 AM | Bangkok | Pop|Variety","logo":"","url":"http:\/\/myradio.plathong.net:8068\/"},{"name":"Samyod Chiang Mai Radio 105.7 FM | Chiang Mai | Pop|World Asia","logo":"","url":"http:\/\/myradio.plathong.net:7002\/"},{"name":"SMF Rock Station | Internet Only | Hard Rock","logo":"","url":"http:\/\/79.143.185.125:8000\/srs1"},{"name":"Start Up Radio Thailand | Internet Only | Pop","logo":"","url":"http:\/\/103.4.216.33:8587"},{"name":"Sukson Radio | Internet Only | Easy Listening","logo":"","url":"http:\/\/stream.pjcdn.com:9000\/Sukson.Radio"},{"name":"T.a.b. radio | Internet Only | News|Talk|Culture","logo":"","url":"http:\/\/103.22.182.145:8400\/tabradio"},{"name":"Thavorn Escape | Internet Only | Chillout|RnB","logo":"","url":"http:\/\/14123.live.streamtheworld.com\/SAM05AAC188_SC"},{"name":"Thavorn Experience | Internet Only | Jazz|Soul","logo":"","url":"http:\/\/14123.live.streamtheworld.com\/SAM05AAC240_SC"},{"name":"The Sound Of Chalong Bay | Internet Only | Latin|Reggae|Zouk and Tropical","logo":"","url":"http:\/\/18193.live.streamtheworld.com\/SAM02AAC176_SC"},{"name":"The Thaiger | Internet Only | Variety","logo":"","url":"http:\/\/stream.radio.co\/s3bc40eca1\/listen"},{"name":"Tourist FM Radio 101 | Krabi | Variety","logo":"","url":"http:\/\/myradio.plathong.net:8672\/"},{"name":"Toyota Union | Internet Only | Variety","logo":"","url":"http:\/\/radios.in.th:9060"},{"name":"Vipak radio | Internet Only | Variety","logo":"","url":"http:\/\/radio12.plathong.net:7066\/;stream.mp3"},{"name":"Voice of Navy | Internet Only | Pop","logo":"","url":"http:\/\/radio12.plathong.net\/7346\/;"},{"name":"Voice of navy 5 Pattaya | Pattaya | Variety","logo":"","url":"http:\/\/myradio.plathong.net:8704"},{"name":"Wink | Internet Only | World Asia","logo":"","url":"http:\/\/radiowink.wink.in.th\/"},{"name":"Yesterday 106.5 FM Phukt Thailand | Phukt | Pop","logo":"","url":"http:\/\/103.246.18.8:4122"},{"name":"COOL Fahrenheit 93","logo":"","category":"Bangkok","url":"http:\/\/111.223.51.7:8000\/;"},{"name":"Cool Celsius 91.5","logo":"","category":"Bangkok","url":"http:\/\/111.223.51.7:8000\/;stream.mp3"},{"name":"90 Rak Thai | Bangkok | World Asia","logo":"","url":"http:\/\/radio11.plathong.net:8896\/"},{"name":"City Radio 90.25 FM | Pattaya | Top 40","logo":"","url":"http:\/\/onair.onair.network:8074\/1\/"},{"name":"MCOT Nongkhai 102.5 FM | Nong Khai | Public","logo":"","url":"http:\/\/rstream.mcot.net:9042"},{"name":"Pattaya Radio 2 | Pattaya | Variety","logo":"","url":"http:\/\/thai-host.com:8100\/pattaya103b"},{"name":"Pattaya Retro Radio | Pattaya | Variety","logo":"","url":"http:\/\/thai-host.com:8100\/pattaya103c"},{"name":"PopRadio | Bangkok | Hits|Pop|RnB","logo":"","url":"http:\/\/streaming.radionomy.com\/-PopRadio"},{"name":"Quk Days Radio 102.00Mhz Sakon Nakhon Thailand | Sakon | Country|Oldies|World","logo":"","url":"http:\/\/radio.ddnsthailand.com:9000\/102mhz\/;"},{"name":"Radio Thailand | Internet Only | News|Children's","logo":"","url":"http:\/\/118.175.16.69:8202\/;"},{"name":"Thai Radio France","logo":"","category":"France","url":"http:\/\/listen.thai-radio.net\/trhq"},{"name":"City Radio Pattaya","logo":"","category":"News","url":"http:\/\/onair22.onair.network:8074\/;"},{"name":"Greetz 102.5 MHz","logo":"null","category":"Acid Jazz","url":"http:\/\/radio4.thzhost.com:8510\/"},{"name":"PassionFM Exclusive Channel \/ 97 Tourist Station","logo":"null","category":"Active Rock","url":"http:\/\/link.onair.network:8058\/;audio.mp3"},{"name":"WatPakBo","logo":"null","category":"News","url":"http:\/\/radio1.siamlivehost.com:8001\/"},{"name":"Capitol.fm","logo":"null","category":"60 years","url":"http:\/\/atlanticthai.primcast.com:5898"},{"name":"Adventist Internet Radio","logo":"null","category":"Soundtracks for films","url":"http:\/\/streaming.radionomy.com\/AdventistInternetRadio"},{"name":"Wow Radio Thailand","logo":"","category":"","url":"http:\/\/radio12.plathong.net:7066"},{"name":"Phuket FM","logo":"","category":"News","url":"http:\/\/148.251.4.92:8000\/pfmMP3"},{"name":"Vipak Radio","logo":"null","category":"Song","url":"http:\/\/radio12.plathong.net:7066\/;"},{"name":"Cool 93 Fahrenheit | Bangkok | Asian Music|Pop","logo":"","url":"http:\/\/111.223.51.7:8000\/;stream\/1"},{"name":"Radio Chiangmai 93.25 FM | Chiangmai | News|Talk|Variety","logo":"","url":"http:\/\/prdonline.prd.go.th:8118"},{"name":"RadioItaly.Asia","logo":"null","category":"","url":"http:\/\/streaming.radionomy.com\/Radio-Italy"},{"name":"Love Radio | Hua Hin | Easy Listening","logo":"","url":"http:\/\/streaming.radionomy.com\/-LoveRadio"},{"name":"RadioItaly.Asia | Internet Only | World Europe","logo":"","url":"http:\/\/streaming.radionomy.com\/-RadioItaly"},{"name":"Sukson Radio | Internet Only | World Asia","logo":"","url":"http:\/\/103.246.18.191:9000\/SuksonRadio"},{"name":"Radio Thailand Phetchabun","logo":"","category":"Ambient","url":"http:\/\/prdonline.prd.go.th:8212\/;stream.mp3"},{"name":"munfm 104.75","logo":"","category":"","url":"http:\/\/103.246.18.3:4018\/;"},{"name":"city life 93.75 fm","logo":"","category":"","url":"http:\/\/onair.onair.network:8076\/;"},{"name":"start up radio fm","logo":"","category":"","url":"http:\/\/103.4.216.33:8587\/;"},{"name":"radio wink thailand","logo":"","category":"","url":"http:\/\/radiowink.wink.in.th\/;"},{"name":"radio thailand fm 88","logo":"","category":"","url":"http:\/\/prdonline.prd.go.th:8200\/;stream.mp3"},{"name":"radio chiangmai fm 98","logo":"","category":"","url":"http:\/\/prdonline.prd.go.th:8120\/;"},{"name":"fm 91","logo":"","category":"","url":"http:\/\/122.155.16.48:8955\/;"},{"name":"smile radio 104.5 fm chantaburi","logo":"","category":"","url":"http:\/\/rcp1.plathong.net:8268\/;"},{"name":"Ê¶Ò¹ÕÇÔ·ÂØàÊÕÂ§¨Ò¡·ËÒÃàÃ×Í15","logo":"","url":"http:\/\/radio12.plathong.net:9934\/"},{"name":"NBT Pheburit FM 95.75","logo":"","url":"http:\/\/118.175.16.69:8010\/"},{"name":"VOICE OF NAVY 5 SATTAHIP","logo":"","url":"http:\/\/radio12.plathong.net:9918\/"},{"name":"FM 97.25 Techno Radio","logo":"","url":"http:\/\/media.login.in.th:8080\/;stream.mp3"},{"name":"FM94.75 WatNaiRong","logo":"","category":"Afro-Beat","url":"http:\/\/radio3.siamlivehost.com:4106"},{"name":"Radio Thailand Maehongson","logo":"","category":"Cinematic","url":"http:\/\/prdonline.prd.go.th:8136\/"},{"name":"Radio Thailand Lampang","logo":"","category":"","url":"http:\/\/118.175.16.69:8066"},{"name":"Education Network Radio Thailand | Internet Only | World Asia","logo":"","url":"http:\/\/prdonline.prd.go.th:8018\/"},{"name":"GSSM | Internet Only | News|Entertainment","logo":"","url":"http:\/\/112.121.151.133:8274\/;*.mp3"},{"name":"KCS Radio","logo":"","url":"http:\/\/radio.servradio.com:8020"},{"name":"MCOT Buri ram 92.0 FM | Buriram | World Asia","logo":"","url":"http:\/\/rstream.mcot.net:9050"},{"name":"Melody Radio 95.75FM","logo":"","url":"http:\/\/radio.chorsaard.net:7028\/;"},{"name":"Radio Thailand AM 837 | Bangkok | World Asia","logo":"","url":"http:\/\/118.175.16.69:8214\/"},{"name":"Radio Thailand Lampang 97.0 FM | Lampang | World Asia","logo":"","url":"http:\/\/202.129.35.2:8018\/"},{"name":"Radio Thailand","logo":"","url":"http:\/\/prdonline.prd.go.th:8038\/"},{"name":"Radio TMD | Internet Only | News|Talk","logo":"","url":"http:\/\/www.radio.tmd.go.th:8014\/;"},{"name":"Radiothailand Nakhonsithammarat | Internet Only | Classic|Country|Asian","logo":"","url":"http:\/\/prd5online.prd.go.th:9010\/;"},{"name":"Voice of navy 5 Sattahip | Sattahip | Variety","logo":"","url":"http:\/\/rcp2.plathong.net:9918"},{"name":"Voice of navy 8 Phitsanulok | Phitsanulok | Variety","logo":"","url":"http:\/\/rcp2.plathong.net:9916"},{"name":"VON4 FM88.75MHz | Chanthaburi | Pop","logo":"","url":"http:\/\/103.22.182.16:7356"},{"name":"WatNaiRong | Internet Only | Talk Buddhist","logo":"","url":"http:\/\/103.7.56.219:4106\/;"},{"name":"Lyrics FM 95","logo":"","category":"Bangkok","url":"http:\/\/rstream.mcot.net:8000\/fm95"},{"name":"Mouthzy Radio 95 FM | Rayong | Top 40","logo":"","url":"http:\/\/103.22.182.153:8266\/"}]